rastreio_correios/__init__.py
rastreio_correios/rastreador.py
rastreio_correios_async-1.0.1.dist-info/LICENSE
rastreio_correios_async-1.0.1.dist-info/WHEEL
rastreio_correios_async-1.0.1.dist-info/METADATA
rastreio_correios_async-1.0.1.dist-info/RECORD
