Metadata-Version: 2.1
Name: rastreio-correios-async
Version: 1.0.1
Summary: Programa não oficial de rastreio de encomendas dos correios.
Author: Diaszano
Author-email: lucasdiiassantos@gmail.com
Requires-Python: >=3.10,<4.0
Classifier: Programming Language :: Python :: 3
Classifier: Programming Language :: Python :: 3.10
Requires-Dist: aiohttp (>=3.8.3,<4.0.0)
